isOdd/__init__.py
isOdd/main.py
isOdd_SomeAspy-1.0.0.dist-info/LICENSE
isOdd_SomeAspy-1.0.0.dist-info/METADATA
isOdd_SomeAspy-1.0.0.dist-info/WHEEL
isOdd_SomeAspy-1.0.0.dist-info/top_level.txt
isOdd_SomeAspy-1.0.0.dist-info/RECORD
