Metadata-Version: 2.1
Name: isOdd-SomeAspy
Version: 1.0.0
Summary: find out if a number is odd xd
Home-page: https://github.com/SomeAspy/idOdd
Author: Aiden
Author-email: amb@aspy.dev
Project-URL: Bug Tracker, https://github.com/SomeAspy/isOdd/issues
Classifier: Programming Language :: Python :: 3
Classifier: License :: OSI Approved :: MIT License
Classifier: Operating System :: OS Independent
Requires-Python: >=3.6
License-File: LICENSE
